{
    "escuchar": "to listen, hear", 
    "correr": "to run", 
    "ayudar": "to help", 
    "alcanzar": "to reach, catch up", 
    "lograr": "to get, obtain, to achieve, attain", 
    "descubrir": "to discover", 
    "cumplir": "to fulfil, carry out", 
    "estudiar": "to study", 
    "preguntar": "to ask, inquire", 
    "jugar": "to play (a game or sport)", 
    "suponer": "to suppose", 
    "aceptar": "to accept, approve, to agree to", 
    "nacer": "to be born", 
    "pagar": "to pay, pay for", 
    "comprender": "to understand, comprehend", 
    "gustar": "to please, be pleasing", 
    "explicar": "to explain", 
    "ofrecer": "to offer", 
    "tocar": "to touch, to play (an instrument)", 
    "realizar": "to achieve, attain, accomplish", 
    "reconocer": "to recognize", 
    "dirigir": "to direct", 
    "utilizar": "to use, utilize", 
    "levantar": "to raise, to lift", 
    "intentar": "to try, attempt"
}